README.md
setup.py
source.json
wordlistcli.py
wordlistcli.egg-info/PKG-INFO
wordlistcli.egg-info/SOURCES.txt
wordlistcli.egg-info/dependency_links.txt
wordlistcli.egg-info/entry_points.txt
wordlistcli.egg-info/requires.txt
wordlistcli.egg-info/top_level.txt