Metadata-Version: 2.1
Name: wordlistcli
Version: 0.1.0
Summary: A command line tool to search and download pre-made wordlist from online archives
Home-page: https://github.com/chessrajat/wordlistcli
Author: Drag0
License: MIT
Keywords: wordlists,discovery,fuzzing
Platform: UNKNOWN
